{"nodes": [{"id": "c_users_sufiy_downloads_dp_scam_dontredeem_utils_and_tests_debug_hf3_py", "label": "debug_hf3.py", "file_type": "code", "source_file": "C:\\Users\\sufiy\\Downloads\\DP Scam\\dontredeem\\utils_and_tests\\debug_hf3.py", "source_location": "L1"}], "edges": [{"source": "c_users_sufiy_downloads_dp_scam_dontredeem_utils_and_tests_debug_hf3_py", "target": "librosa", "relation": "imports", "confidence": "EXTRACTED", "source_file": "C:\\Users\\sufiy\\Downloads\\DP Scam\\dontredeem\\utils_and_tests\\debug_hf3.py", "source_location": "L1", "weight": 1.0}, {"source": "c_users_sufiy_downloads_dp_scam_dontredeem_utils_and_tests_debug_hf3_py", "target": "transformers", "relation": "imports_from", "confidence": "EXTRACTED", "source_file": "C:\\Users\\sufiy\\Downloads\\DP Scam\\dontredeem\\utils_and_tests\\debug_hf3.py", "source_location": "L2", "weight": 1.0}], "raw_calls": []}